[
    {
        "call_time": null, 
        "duration": 37.586878716014326, 
        "performance_counters": {
            "num_requested_bytes": 62180733, 
            "num_requests": 4, 
            "num_requested_chunks": 14959
        }, 
        "args": [
            "'/uscms/home/bean/nobackup/tagnprobe/DY_2023_1.root'", 
            "'Events'", 
            "0", 
            "1", 
            "False"
        ], 
        "kwargs": [], 
        "exception": null, 
        "message": null, 
        "fqdn": null, 
        "hostname": null
    }
]